{"vue_index.md":"CAEfuy6C","nestjs_index.md":"BAWziGve","css_index.md":"weyuzjjh","dailyrecord_index.md":"Dj005-QM","thewayforward_index.md":"D9OT5Np5","rotelearning_index.md":"xgwXVMhy","test.md":"cBH6Wpsc","react_index.md":"B02F9Jr5","nav_index.md":"DX9gU5SG","js_index.md":"CJ65jrTH","excellentarticle_2024-04-16_index.md":"CYBiPlYV","excellentarticle_index.md":"CB66Shoz","html_index.md":"Cy_Xn0EX","excellentarticle_2024-04-11_index.md":"D-GRYctr","workexperience_index.md":"DFB1vFYr","excellentarticle_2024-04-12_index.md":"DBlI8E2K","excellentarticle_2024-04-17_index.md":"B9FrRWzg","test_index.md":"CXG-8Nqf","excellentarticle_2024-04-15_index.md":"Cdff01jR","rotelearning_vue_index.md":"BwI3Ops3","index.md":"Cnp8w-wO","rotelearning_react_index.md":"eKJ2fsR9"}
